grammar/BasicToken.py
grammar/Document.py
grammar/DocumentObject.py
grammar/Entity.py
grammar/EntityChunk.py
grammar/EntityType.py
grammar/NounChunk.py
grammar/Token.py
grammar/TokenSpan.py
grammar/__init__.py
grammar/dependency_definitions.py
grammar/join_punctuation.py
grammar/part_of_speach_definitions.py
grammar/remove_list_duplicates.py
grammar-1.6.dist-info/LICENSE
grammar-1.6.dist-info/METADATA
grammar-1.6.dist-info/WHEEL
grammar-1.6.dist-info/top_level.txt
grammar-1.6.dist-info/RECORD
